{
  "type": "forge:conditional",
  "recipes": [
    {
      "conditions": [
        {
          "value": {
            "tag": "forge:nuggets/aluminum",
            "type": "forge:tag_empty"
          },
          "type": "forge:not"
        }
      ],
      "recipe": {
        "type": "oreberriesreplanted:blasting",
        "ingredient": {
          "item": "oreberriesreplanted:aluminum_oreberry"
        },
        "result": {
          "tag": "forge:nuggets/aluminum"
        },
        "experience": 0.2,
        "cookingtime": 100
      }
    }
  ]
}
